README.rst
setup.py
distlog/__init__.py
distlog.egg-info/PKG-INFO
distlog.egg-info/SOURCES.txt
distlog.egg-info/dependency_links.txt
distlog.egg-info/top_level.txt
distlog/logger/__init__.py
distlog/logger/context.py
distlog/logger/formatters.py
distlog/logger/handler.py
distlogd/__init__.py
distlogd/daemon3x.py
distlogd/main.py
distlogd/plugin.py
distlogd/plugins/__init__.py
distlogd/plugins/forward/__init__.py