Metadata-Version: 1.1
Name: distlog
Version: 0.1.dev0
Summary: Logging for distributed systems.
Home-page: https://github.com/lnoor/distlog
Author: Leo Noordergraaf
Author-email: leo@noordergraaf.net
License: GPLv3
Keywords: scoped structured distributed logging
Platform: any
Classifier: Development Status :: 2 - Pre-Alpha
Classifier: Environment :: Other Environment
Classifier: Intended Audience :: Developers
Classifier: License :: OSI Approved :: GNU General Public License v3 (GPLv3)
Classifier: Operating System :: OS Independent
Classifier: Programming Language :: Python :: 2.7
Classifier: Programming Language :: Python :: 3.4
Classifier: Topic :: System :: Logging
Classifier: Topic :: Utilities
